{
    "folder": "-at-2/1724_fricx_jeremie",
    "offset": 37,
    "min": -36,
    "max": 690,
    "chapters": [
        ["titre", -31],
        ["préface", -29],
        ["approbations", -1],
        [1, 1],
        [2, 12],
        [3, 32],
        [4, 47],
        [5, 64],
        [6, 79],
        [7, 94],
        [8, 107],
        [9, 118],
        [10, 130],
        [11, 142],
        [12, 157],
        [13, 170],
        [14, 185],
        [15, 195],
        [16, 210],
        [17, 221],
        [18, 234],
        [19, 245],
        [20, 253],
        [21, 265],
        [22, 274],
        [23, 290],
        [24, 309],
        [25, 317],
        [26, 333],
        [27, 345],
        [28, 355],
        [29, 364],
        [30, 380],
        [31, 394],
        [32, 416],
        [33, 431],
        [34, 444],
        [35, 453],
        [36, 464],
        [37, 478],
        [38, 488],
        [39, 502],
        [40, 510],
        [41, 522],
        [42, 531],
        [43, 542],
        [44, 552],
        [45, 568],
        [46, 571],
        [47, 586],
        [48, 591],
        [49, 610],
        [50, 626],
        [51, 647],
        [52, 677]
    ]
}